adver_mng
