Metadata-Version: 1.0
Name: adver-mng
Version: 0.1.2
Summary: forbid spiders
Home-page: http://www.vimer.cn
Author: dantezhu
Author-email: zny2008@gmail.com
License: BSD
Platform: any
